core/__init__.py
core/core.py
data/train.csv
exampleJPAH-0.1.dist-info/DESCRIPTION.rst
exampleJPAH-0.1.dist-info/METADATA
exampleJPAH-0.1.dist-info/RECORD
exampleJPAH-0.1.dist-info/WHEEL
exampleJPAH-0.1.dist-info/entry_points.txt
exampleJPAH-0.1.dist-info/metadata.json
exampleJPAH-0.1.dist-info/top_level.txt
main/__init__.py
main/main.py
readingData/__init__.py
readingData/readingData.py
