Metadata-Version: 2.0
Name: exampleJPAH
Version: 0.1
Summary: A example Python project
Home-page: UNKNOWN
Author: jose Romero & Alvaro Hernandez
Author-email: u125149@usal.es
License: MIT
Keywords: example machine learning development
Platform: UNKNOWN
Classifier: Development Status :: 3 - Alpha
Classifier: Intended Audience :: Developers
Classifier: Topic :: Software Development :: Build Tools
Classifier: License :: OSI Approved :: MIT License
Classifier: Programming Language :: Python :: 2.7
Requires-Dist: numpy
Requires-Dist: pandas (>=0.20)
Requires-Dist: scikit-learn (==0.18.1)
Requires-Dist: scipy
